muxes.v
//Universidad del Valle de Guatemala
//Gerardo Fuentes
//19389

module mux2(input [1:0]d0, input s, output y);

  assign y = s ? d0[1]:d0[0];

endmodule

module mux4(input [3:0]d1, input[1:]s1, output y1)

  mux2 m1();
  mux2 m2();

muxes_tb.v
//Universidad del Valle de Guatemala
//Gerardo Fuentes
//19389

module testbench();

  reg [1:0]d0;
  reg s;
  wire y;

  mux2 M1(d0, s, y);

  initial begin
  #1
    $display("\n");
    $display("Todas las ecuaciones");
    $display("s b c | y");
    $display("------|---");
    $monitor("%b %b %b | %b", s, d0[1], d0[0], y);
       s = 0; d0[1] = 0; d0[0] = 0;
    #1 s = 0; d0[1] = 0; d0[0] = 1;
    #1 s = 0; d0[1] = 1; d0[0] = 0;
    #1 s = 0; d0[1] = 1; d0[0] = 1;
    #1 s = 1; d0[1] = 0; d0[0] = 0;
    #1 s = 1; d0[1] = 0; d0[0] = 1;
    #1 s = 1; d0[1] = 1; d0[0] = 0;
    #1 s = 1; d0[1] = 1; d0[0] = 1;
  end

  initial
    #20 $finish;

  initial begin
    $dumpfile("muxes_tb.vcd");
    $dumpvars(0, testbench);
  end

endmodule

muxes_tb.vcd
$date
	Sat Aug 15 19:40:52 2020
$end
$version
	Icarus Verilog
$end
$timescale
	1ps
$end
$scope module testbench $end
$var wire 1 ! y $end
$var reg 2 " d0 [1:0] $end
$var reg 1 # s $end
$scope module M1 $end
$var wire 2 $ d0 [1:0] $end
$var wire 1 # s $end
$var wire 1 ! y $end
$upscope $end
$upscope $end
$enddefinitions $end
#0
$dumpvars
bx $
x#
bx "
x!
$end
#1
0!
b0 "
b0 $
0#
#2
1!
b1 "
b1 $
#3
0!
b10 "
b10 $
#4
1!
b11 "
b11 $
#5
0!
b0 "
b0 $
1#
#6
b1 "
b1 $
#7
1!
b10 "
b10 $
#8
b11 "
b11 $
